apronpy/__init__.py
apronpy/abstract0.py
apronpy/abstract1.py
apronpy/box.py
apronpy/cdll.py
apronpy/coeff.py
apronpy/dimension.py
apronpy/environment.py
apronpy/interval.py
apronpy/lincons0.py
apronpy/lincons1.py
apronpy/linexpr0.py
apronpy/linexpr1.py
apronpy/manager.py
apronpy/mpfr.py
apronpy/mpq.py
apronpy/mpz.py
apronpy/oct.py
apronpy/polka.py
apronpy/scalar.py
apronpy/t1p.py
apronpy/tcons0.py
apronpy/tcons1.py
apronpy/texpr0.py
apronpy/texpr1.py
apronpy/var.py
apronpy-1.0.11.dist-info/licenses/LICENSE
apronpy-1.0.11.dist-info/METADATA
apronpy-1.0.11.dist-info/WHEEL
apronpy-1.0.11.dist-info/top_level.txt
apronpy-1.0.11.dist-info/RECORD
