Metadata-Version: 2.4
Name: apronpy
Version: 1.0.11
Summary: Python Interface for the APRON Numerical Abstract Domain Library
Home-page: https://github.com/caterinaurban/apronpy
Author: Caterina Urban
Author-email: caterina.urban@gmail.com
License-File: LICENSE
Dynamic: author
Dynamic: author-email
Dynamic: description
Dynamic: description-content-type
Dynamic: home-page
Dynamic: license-file
Dynamic: summary
